OTMODE/OTMODE_code.py
OTMODE/__init__.py
otmode-0.3.0.dist-info/licenses/LICENSE
otmode-0.3.0.dist-info/METADATA
otmode-0.3.0.dist-info/WHEEL
otmode-0.3.0.dist-info/top_level.txt
otmode-0.3.0.dist-info/RECORD
