Metadata-Version: 2.4
Name: OTMODE
Version: 0.3.0
Summary: OTMODE is a computational framework built on Optimal Transport (OT) theory for improving cell-type annotation accuracy and for identifying differential features across conditions in single-cell multi-omics data.
Home-page: https://github.com/Eggong/OTMODE
Author: Lanks Huidong Su
Author-email: u3010549@conect.hku.hk
License: MIT
Classifier: Programming Language :: Python :: 3
Classifier: License :: OSI Approved :: MIT License
Classifier: Topic :: Scientific/Engineering :: Bio-Informatics
Classifier: Programming Language :: Python :: 3.8
Classifier: Programming Language :: Python :: 3.9
Classifier: Programming Language :: Python :: 3.10
Classifier: Programming Language :: Python :: 3.11
Classifier: Operating System :: OS Independent
Requires-Python: >=3.8
License-File: LICENSE
Requires-Dist: POT==0.9.5
Requires-Dist: anndata>=0.10.9
Provides-Extra: dev
Requires-Dist: build; extra == "dev"
Requires-Dist: twine; extra == "dev"
Dynamic: author
Dynamic: author-email
Dynamic: classifier
Dynamic: description
Dynamic: description-content-type
Dynamic: home-page
Dynamic: license
Dynamic: license-file
Dynamic: requires-dist
Dynamic: requires-python
Dynamic: summary
